pyride/__init__.py
pyride/__main__.py
pyride/core.py
pyride/data.py
pyride/pathway.py
pyride/simple_request.py
pyride/util.py
pyride/widgets.py
PYRIDE-0.0.1.dev19.dist-info/LICENSE.txt
PYRIDE-0.0.1.dev19.dist-info/METADATA
PYRIDE-0.0.1.dev19.dist-info/WHEEL
PYRIDE-0.0.1.dev19.dist-info/entry_points.txt
PYRIDE-0.0.1.dev19.dist-info/top_level.txt
PYRIDE-0.0.1.dev19.dist-info/RECORD
